desktop.ini
findmyfile/__init__.py
findmyfile/findmyfile.py
findmyfile-0.2.4.dist-info/LICENCE.txt
findmyfile-0.2.4.dist-info/METADATA
findmyfile-0.2.4.dist-info/WHEEL
findmyfile-0.2.4.dist-info/entry_points.txt
findmyfile-0.2.4.dist-info/top_level.txt
findmyfile-0.2.4.dist-info/RECORD
